MANIFEST.in
README.md
setup.py
scripts/find_store
storelocator/__init__.py
storelocator/constants.py
storelocator/csv_parser.py
storelocator/util.py
storelocator.egg-info/PKG-INFO
storelocator.egg-info/SOURCES.txt
storelocator.egg-info/dependency_links.txt
storelocator.egg-info/requires.txt
storelocator.egg-info/top_level.txt
storelocator/csv/store-locations.csv