Metadata-Version: 2.1
Name: storelocator
Version: 1.0.5
Summary: Command-line tool to find nearest store.
Home-page: https://github.com/austinbrown34/StoreLocator
Author: Austin Brown
Author-email: austinbrown34@gmail.com
License: UNKNOWN
Platform: UNKNOWN
